{"name":"t:sections.footer.name","type":"footer","sections":{"footer":{"type":"footer","blocks":{"140ea8b8-04a4-4b0f-bc1d-a0a7d943d6fd":{"type":"link_list","settings":{"heading":"","menu":"footer"}}},"block_order":["140ea8b8-04a4-4b0f-bc1d-a0a7d943d6fd"],"custom_css":[],"settings":{"color_scheme":"background-1","newsletter_enable":false,"newsletter_heading":"NEWSLETTER","enable_follow_on_shop":true,"show_social":false,"enable_country_selector":true,"enable_language_selector":false,"payment_enable":false,"show_policy":false,"margin_top":0,"padding_top":40,"padding_bottom":28}}},"order":["footer"]}